mkdocs_revealjs/__init__.py
mkdocs_revealjs/ci.py
mkdocs_revealjs/exclude.py
mkdocs_revealjs/plugin.py
mkdocs_revealjs/util.py
mkdocs_revealjs-0.0.6.dist-info/LICENSE
mkdocs_revealjs-0.0.6.dist-info/METADATA
mkdocs_revealjs-0.0.6.dist-info/WHEEL
mkdocs_revealjs-0.0.6.dist-info/entry_points.txt
mkdocs_revealjs-0.0.6.dist-info/top_level.txt
mkdocs_revealjs-0.0.6.dist-info/RECORD
